MBPython/__init__.py
MBPython/bindwebview.py
MBPython/callback.py
MBPython/cookie.py
MBPython/jsrunpy.py
MBPython/message.py
MBPython/method.py
MBPython/miniblink.py
MBPython/network.py
MBPython/proxy.py
MBPython/pyrunjs.py
MBPython/screenshot.py
MBPython/seticon.py
MBPython/timer.py
MBPython/winConst.py
MBPython/window.py
MBPython/wkeStruct.py
MBPython/wndproc.py
mbpython-0.2.2.dist-info/WHEEL
mbpython-0.2.2.dist-info/METADATA
mbpython-0.2.2.dist-info/RECORD
