Metadata-Version: 2.1
Name: mbpython
Version: 0.2.2
Summary: Miniblink binding for python
Home-page: https://github.com/lochen88/MBPython
License: MIT
Author: lochen
Author-email: 1191826896@qq.com
Requires-Python: >=3.6,<4.0
Classifier: License :: OSI Approved :: MIT License
Classifier: Programming Language :: Python :: 3
Classifier: Programming Language :: Python :: 3.6
Classifier: Programming Language :: Python :: 3.7
Classifier: Programming Language :: Python :: 3.8
Classifier: Programming Language :: Python :: 3.9
Requires-Dist: pywin32 (>=228,<229)
Project-URL: Repository, https://github.com/lochen88/MBPython
